README.rst
dmp_core.py
setup.cfg
setup.py
ga_dmp_hdf5.egg-info/PKG-INFO
ga_dmp_hdf5.egg-info/SOURCES.txt
ga_dmp_hdf5.egg-info/dependency_links.txt
ga_dmp_hdf5.egg-info/requires.txt
ga_dmp_hdf5.egg-info/top_level.txt