Metadata-Version: 1.0
Name: ga-dmp-hdf5
Version: 0.1
Summary: Tools for creating hdf5 files in GA's DMP format
Home-page: UNKNOWN
Author: Richard Kalling
Author-email: UNKNOWN
License: MIT
Platform: UNKNOWN
